setup.cfg
setup.py
src/BCSFE_Python_Discord/__init__.py
src/BCSFE_Python_Discord/__main__.py
src/BCSFE_Python_Discord/adb_handler.py
src/BCSFE_Python_Discord/config_manager.py
src/BCSFE_Python_Discord/csv_handler.py
src/BCSFE_Python_Discord/feature_handler.py
src/BCSFE_Python_Discord/game_data_getter.py
src/BCSFE_Python_Discord/helper.py
src/BCSFE_Python_Discord/item.py
src/BCSFE_Python_Discord/locale_handler.py
src/BCSFE_Python_Discord/managed_item.py
src/BCSFE_Python_Discord/parse_save.py
src/BCSFE_Python_Discord/patcher.py
src/BCSFE_Python_Discord/py.typed
src/BCSFE_Python_Discord/root_handler.py
src/BCSFE_Python_Discord/serialise_save.py
src/BCSFE_Python_Discord/server_handler.py
src/BCSFE_Python_Discord/tracker.py
src/BCSFE_Python_Discord/updater.py
src/BCSFE_Python_Discord/user_input_handler.py
src/BCSFE_Python_Discord/edits/__init__.py
src/BCSFE_Python_Discord/edits/basic/__init__.py
src/BCSFE_Python_Discord/edits/basic/basic_items.py
src/BCSFE_Python_Discord/edits/basic/catfruit.py
src/BCSFE_Python_Discord/edits/basic/catseyes.py
src/BCSFE_Python_Discord/edits/basic/ototo_base_mats.py
src/BCSFE_Python_Discord/edits/basic/talent_orbs.py
src/BCSFE_Python_Discord/edits/basic/talent_orbs_new.py
src/BCSFE_Python_Discord/edits/cats/__init__.py
src/BCSFE_Python_Discord/edits/cats/cat_helper.py
src/BCSFE_Python_Discord/edits/cats/cat_id_selector.py
src/BCSFE_Python_Discord/edits/cats/chara_drop.py
src/BCSFE_Python_Discord/edits/cats/clear_cat_guide.py
src/BCSFE_Python_Discord/edits/cats/evolve_cats.py
src/BCSFE_Python_Discord/edits/cats/get_remove_cats.py
src/BCSFE_Python_Discord/edits/cats/talents.py
src/BCSFE_Python_Discord/edits/cats/upgrade_blue.py
src/BCSFE_Python_Discord/edits/cats/upgrade_cats.py
src/BCSFE_Python_Discord/edits/gamototo/__init__.py
src/BCSFE_Python_Discord/edits/gamototo/fix_gamatoto.py
src/BCSFE_Python_Discord/edits/gamototo/gamatoto_xp.py
src/BCSFE_Python_Discord/edits/gamototo/helpers.py
src/bcsfe_iosapi.egg-info/PKG-INFO
src/bcsfe_iosapi.egg-info/SOURCES.txt
src/bcsfe_iosapi.egg-info/dependency_links.txt
src/bcsfe_iosapi.egg-info/requires.txt
src/bcsfe_iosapi.egg-info/top_level.txt