Metadata-Version: 2.1
Name: bcsfe-iosapi
Version: 2.7.69
Summary: BCSFE_Python personal api
Home-page: 
Author: CintagramABP
Requires-Python: >=3.9
Provides-Extra: testing
